lite_slurm-1.0.5.dist-info/licenses/LICENSE
task_manager/__init__.py
task_manager/cli.py
task_manager/config.py
task_manager/core.py
task_manager/email.py
task_manager/monitor.py
task_manager/config/email_config.json
lite_slurm-1.0.5.dist-info/METADATA
lite_slurm-1.0.5.dist-info/WHEEL
lite_slurm-1.0.5.dist-info/entry_points.txt
lite_slurm-1.0.5.dist-info/top_level.txt
lite_slurm-1.0.5.dist-info/RECORD
