Metadata-Version: 2.4
Name: lite-slurm
Version: 1.0.5
Summary: A tmux-based task scheduling and monitoring tool
Home-page: https://github.com/zz9tf/slurm-like-task-manager
Author: zheng
Author-email: zheng <zheng.zheng.luck@gmail.com>
License: MIT
Project-URL: Homepage, https://github.com/zz9tf/slurm-like-task-manager
Project-URL: Bug Reports, https://github.com/zz9tf/slurm-like-task-manager/issues
Project-URL: Source, https://github.com/zz9tf/slurm-like-task-manager
Project-URL: Documentation, https://github.com/zz9tf/slurm-like-task-manager#readme
Classifier: Development Status :: 4 - Beta
Classifier: Intended Audience :: Developers
Classifier: License :: OSI Approved :: MIT License
Classifier: Operating System :: POSIX :: Linux
Classifier: Programming Language :: Python :: 3
Classifier: Programming Language :: Python :: 3.7
Classifier: Programming Language :: Python :: 3.8
Classifier: Programming Language :: Python :: 3.9
Classifier: Programming Language :: Python :: 3.10
Classifier: Programming Language :: Python :: 3.11
Classifier: Topic :: System :: Systems Administration
Classifier: Topic :: Utilities
Requires-Python: >=3.7
License-File: LICENSE
Requires-Dist: psutil>=5.8.0
Requires-Dist: google-auth>=2.0.0
Requires-Dist: google-auth-oauthlib>=0.5.0
Requires-Dist: google-auth-httplib2>=0.1.0
Requires-Dist: google-api-python-client>=2.0.0
Provides-Extra: dev
Requires-Dist: pytest>=6.0; extra == "dev"
Requires-Dist: pytest-cov>=2.0; extra == "dev"
Requires-Dist: black>=21.0; extra == "dev"
Requires-Dist: flake8>=3.8; extra == "dev"
Dynamic: author
Dynamic: home-page
Dynamic: license-file
Dynamic: requires-python
